[
  {
    "1": {
      "value": "Mark of the Kindred",
      "description": "Necessary: Used for identification."
    },
    "disp_name": {
      "value": "",
      "description": "Name of the ability\nOnly necessary if the value differs from Mark of the Kindred."
    },
    "champion": {
      "value": "Kindred",
      "description": "champion"
    },
    "skill": {
      "value": "I",
      "description": "skill"
    },
    "range": {
      "value": "",
      "description": "range (deprecated)"
    },
    "target range": {
      "value": "",
      "description": "target range"
    },
    "attack range": {
      "value": "",
      "description": "attack range"
    },
    "travel distance": {
      "value": "",
      "description": "travel distance"
    },
    "collision radius": {
      "value": "",
      "description": "collision radius"
    },
    "effect radius": {
      "value": "",
      "description": "effect radius"
    },
    "width": {
      "value": "",
      "description": "width"
    },
    "angle": {
      "value": "",
      "description": "angle"
    },
    "inner radius": {
      "value": "",
      "description": "inner radius"
    },
    "tether radius": {
      "value": "",
      "description": "tether radius"
    },
    "speed": {
      "value": "",
      "description": "speed"
    },
    "cast time": {
      "value": "",
      "description": "cast time"
    },
    "cost": {
      "value": "",
      "description": "cost"
    },
    "costtype": {
      "value": "",
      "description": "costtype"
    },
    "static": {
      "value": "40 / 75",
      "description": "static"
    },
    "cooldown": {
      "value": "",
      "description": "cooldown"
    },
    "ontargetcd": {
      "value": "",
      "description": "ontargetcd"
    },
    "ontargetcdstatic": {
      "value": "240",
      "description": "ontargetcdstatic"
    },
    "recharge": {
      "value": "",
      "description": "recharge"
    },
    "rechargestatic": {
      "value": "",
      "description": "rechargestatic"
    },
    "customlabel": {
      "value": "",
      "description": "customlabel"
    },
    "custominfo": {
      "value": "",
      "description": "custominfo"
    },
    "icon": {
      "value": "Mark of the Kindred.png",
      "description": "icon"
    },
    "blurb": {
      "value": "Kindred can mark targets to Hunt. Successfully completing a Hunt permanently empowers Kindred's basic abilities. Every 4 hunts completed also increases Kindred's basic attack range.",
      "description": "blurb"
    },
    "blurb2": {
      "value": "",
      "description": "blurb2"
    },
    "description": {
      "value": "Innate: Both Lamb and Wolf mark targets to hunt. Scoring a <img src=\"https://vignette.wikia.nocookie.net/leagueoflegends/images/0/07/Damage_rating.png/revision/latest/scale-to-width-down/20?cb=20170514053710\" \t alt=\"Damage rating\"  \tclass=\"\" \t \tdata-image-key=\"Damage_rating.png\" \tdata-image-name=\"Damage rating.png\" \t \t width=\"20\"  \t height=\"20\"  \t \t \t \t> takedown on a marked target permanently empowers Kindred's abilities, as well as granting Lamb 75 − 250 (based on Marks) <img src=\"https://vignette.wikia.nocookie.net/leagueoflegends/images/1/13/Range_icon.png/revision/latest/scale-to-width-down/15?cb=20170715002053\" \t alt=\"Range icon\"  \tclass=\"\" \t \tdata-image-key=\"Range_icon.png\" \tdata-image-name=\"Range icon.png\" \t \t width=\"15\"  \t height=\"15\"  \t \t \t \t> bonus range on her basic attacks and abilities.",
      "description": "description"
    },
    "leveling": {
      "value": "",
      "description": "leveling"
    },
    "icon2": {
      "value": "Lamb's Mask profileicon.png",
      "description": "icon2"
    },
    "description2": {
      "value": "Innate - Lamb: Lamb is offered a selection of enemy <img src=\"https://vignette.wikia.nocookie.net/leagueoflegends/images/2/25/Champion_icon.png/revision/latest/scale-to-width-down/20?cb=20181122022630\" \t alt=\"Champion icon\"  \tclass=\"\" \t \tdata-image-key=\"Champion_icon.png\" \tdata-image-name=\"Champion icon.png\" \t \t width=\"20\"  \t height=\"20\"  \t \t \t \t> champions to take down, which is hidden while in combat with an enemy champion. Once selected, there's an 8 second delay before the Mark can be collected, and Lamb can change her target if the target hasn't died during a period of time. Targets successfully hunted cannot be targeted again for 4 minutes.",
      "description": "description2"
    },
    "leveling2": {
      "value": "",
      "description": "leveling2"
    },
    "icon3": {
      "value": "Wolf's Mask profileicon.png",
      "description": "icon3"
    },
    "description3": {
      "value": "Innate - Wolf: Starting at 3:15, Wolf periodically selects a <img src=\"https://vignette.wikia.nocookie.net/leagueoflegends/images/d/d1/Monster_icon.png/revision/latest?cb=20181123222641\" \t alt=\"Monster icon\"  \tclass=\"\" \t \tdata-image-key=\"Monster_icon.png\" \tdata-image-name=\"Monster icon.png\" \t \t width=\"20\"  \t height=\"20\"  \t \t \t \t> monster camp within the enemy's jungle based on Lamb's current Marks for 180 seconds:\n 0 : <img src=\"https://vignette.wikia.nocookie.net/leagueoflegends/images/a/a2/Rift_ScuttlerSquare.png/revision/latest/scale-to-width-down/20?cb=20141111231735\" \t alt=\"Rift ScuttlerSquare\"  \tclass=\"thumbborder \" \t \tdata-image-key=\"Rift_ScuttlerSquare.png\" \tdata-image-name=\"Rift ScuttlerSquare.png\" \t \t width=\"20\"  \t height=\"20\"  \t \t \t \t> Rift Scuttler\n 1 – 3: <img src=\"https://vignette.wikia.nocookie.net/leagueoflegends/images/a/a2/Rift_ScuttlerSquare.png/revision/latest/scale-to-width-down/20?cb=20141111231735\" \t alt=\"Rift ScuttlerSquare\"  \tclass=\"thumbborder \" \t \tdata-image-key=\"Rift_ScuttlerSquare.png\" \tdata-image-name=\"Rift ScuttlerSquare.png\" \t \t width=\"20\"  \t height=\"20\"  \t \t \t \t> Rift Scuttler, <img src=\"https://vignette.wikia.nocookie.net/leagueoflegends/images/9/94/Crimson_RaptorSquare.png/revision/latest/scale-to-width-down/20?cb=20161029234307\" \t alt=\"Crimson RaptorSquare\"  \tclass=\"thumbborder \" \t \tdata-image-key=\"Crimson_RaptorSquare.png\" \tdata-image-name=\"Crimson RaptorSquare.png\" \t \t width=\"20\"  \t height=\"20\"  \t \t \t \t> Crimson Raptor, <img src=\"https://vignette.wikia.nocookie.net/leagueoflegends/images/e/e8/GrompSquare.png/revision/latest/scale-to-width-down/20?cb=20161029234737\" \t alt=\"GrompSquare\"  \tclass=\"thumbborder \" \t \tdata-image-key=\"GrompSquare.png\" \tdata-image-name=\"GrompSquare.png\" \t \t width=\"20\"  \t height=\"20\"  \t \t \t \t> Gromp\n 4 – 7: <img src=\"https://vignette.wikia.nocookie.net/leagueoflegends/images/f/fe/Ancient_KrugSquare.png/revision/latest/scale-to-width-down/20?cb=20170408140308\" \t alt=\"Ancient KrugSquare\"  \tclass=\"thumbborder \" \t \tdata-image-key=\"Ancient_KrugSquare.png\" \tdata-image-name=\"Ancient KrugSquare.png\" \t \t width=\"20\"  \t height=\"20\"  \t \t \t \t> Ancient Krug, <img src=\"https://vignette.wikia.nocookie.net/leagueoflegends/images/8/85/Blue_SentinelSquare.png/revision/latest/scale-to-width-down/20?cb=20140620025405\" \t alt=\"Blue SentinelSquare\"  \tclass=\"thumbborder \" \t \tdata-image-key=\"Blue_SentinelSquare.png\" \tdata-image-name=\"Blue SentinelSquare.png\" \t \t width=\"20\"  \t height=\"20\"  \t \t \t \t> Blue Sentinel, <img src=\"https://vignette.wikia.nocookie.net/leagueoflegends/images/d/d6/Greater_Murk_WolfSquare.png/revision/latest/scale-to-width-down/20?cb=20141111151412\" \t alt=\"Greater Murk WolfSquare\"  \tclass=\"thumbborder \" \t \tdata-image-key=\"Greater_Murk_WolfSquare.png\" \tdata-image-name=\"Greater Murk WolfSquare.png\" \t \t width=\"20\"  \t height=\"20\"  \t \t \t \t> Greater Murk Wolf, or <img src=\"https://vignette.wikia.nocookie.net/leagueoflegends/images/e/e7/Red_BramblebackSquare.png/revision/latest/scale-to-width-down/20?cb=20140620025406\" \t alt=\"Red BramblebackSquare\"  \tclass=\"thumbborder \" \t \tdata-image-key=\"Red_BramblebackSquare.png\" \tdata-image-name=\"Red BramblebackSquare.png\" \t \t width=\"20\"  \t height=\"20\"  \t \t \t \t> Red Brambleback\n 8 + : <img src=\"https://vignette.wikia.nocookie.net/leagueoflegends/images/c/c3/Rift_HeraldSquare.png/revision/latest/scale-to-width-down/20?cb=20171112190027\" \t alt=\"Rift HeraldSquare\"  \tclass=\"thumbborder \" \t \tdata-image-key=\"Rift_HeraldSquare.png\" \tdata-image-name=\"Rift HeraldSquare.png\" \t \t width=\"20\"  \t height=\"20\"  \t \t \t \t> Rift Herald or <img src=\"https://vignette.wikia.nocookie.net/leagueoflegends/images/3/38/Baron_NashorSquare.png/revision/latest/scale-to-width-down/20?cb=20140620025404\" \t alt=\"Baron NashorSquare\"  \tclass=\"thumbborder \" \t \tdata-image-key=\"Baron_NashorSquare.png\" \tdata-image-name=\"Baron NashorSquare.png\" \t \t width=\"20\"  \t height=\"20\"  \t \t \t \t> Baron Nashor, <img src=\"https://vignette.wikia.nocookie.net/leagueoflegends/images/c/c9/DragonSquare.png/revision/latest/scale-to-width-down/20?cb=20140620025407\" \t alt=\"DragonSquare\"  \tclass=\"thumbborder \" \t \tdata-image-key=\"DragonSquare.png\" \tdata-image-name=\"DragonSquare.png\" \t \t width=\"20\"  \t height=\"20\"  \t \t \t \t> Dragon or <img src=\"https://vignette.wikia.nocookie.net/leagueoflegends/images/3/34/Elder_DragonSquare.png/revision/latest/scale-to-width-down/20?cb=20170408123953\" \t alt=\"Elder DragonSquare\"  \tclass=\"thumbborder \" \t \tdata-image-key=\"Elder_DragonSquare.png\" \tdata-image-name=\"Elder DragonSquare.png\" \t \t width=\"20\"  \t height=\"20\"  \t \t \t \t> Elder Dragon\n\nWolf will select another monster camp 40 seconds after killing a marked monster. If an ally kills a hunted jungle monster within 6 seconds of Kindred damaging it, Kindred will still acquire the stack.\nThe marked camp is highlighted on the mini map to both teams. The mark is removed when the camp is cleared even if Kindred are not involved.",
      "description": "description3"
    },
    "leveling3": {
      "value": "",
      "description": "leveling3"
    },
    "icon4": {
      "value": "",
      "description": "icon4"
    },
    "description4": {
      "value": "",
      "description": "description4"
    },
    "leveling4": {
      "value": "",
      "description": "leveling4"
    },
    "icon5": {
      "value": "",
      "description": "icon5"
    },
    "description5": {
      "value": "",
      "description": "description5"
    },
    "leveling5": {
      "value": "",
      "description": "leveling5"
    },
    "targeting": {
      "value": "Passive",
      "description": "Permafrost is a single target ability."
    },
    "affects": {
      "value": "Self, Enemies",
      "description": "Permafrost affects enemy champions and large monsters"
    },
    "damagetype": {
      "value": "",
      "description": "Permafrost deals magic damage."
    },
    "spelleffects": {
      "value": "",
      "description": "spelleffects"
    },
    "onhiteffects": {
      "value": "",
      "description": "onhiteffects can be set to 'true', for abilities that apply on-hit effects (from items or other abilities)"
    },
    "occurrence": {
      "value": "",
      "description": "occurrence can either be set to 'hit' or 'attack', and refers to on-hit effects"
    },
    "spellshield": {
      "value": "",
      "description": "spellshield can either be set to true, or written with a custom description."
    },
    "projectile": {
      "value": "",
      "description": "true"
    },
    "callforhelp": {
      "value": "",
      "description": "callforhelp determines whether minion aggro will transfer to the caster"
    },
    "additional": {
      "value": "",
      "description": "Displays additional information in a smaller window below the template."
    },
    "notes": {
      "value": "* No additional notes.",
      "description": "Displays additional information with effect table to the right."
    },
    "flavorsound": {
      "value": "",
      "description": "flavor sound"
    },
    "video": {
      "value": "",
      "description": "video"
    },
    "video2": {
      "value": "",
      "description": "video 2"
    },
    "yvideo": {
      "value": "",
      "description": "YouTube video"
    },
    "yvideo2": {
      "value": "",
      "description": "YouTube video 2"
    }
  },
  {
    "1": {
      "value": "Dance of Arrows",
      "description": "Necessary: Used for identification."
    },
    "disp_name": {
      "value": "",
      "description": "Name of the ability\nOnly necessary if the value differs from Dance of Arrows."
    },
    "champion": {
      "value": "Kindred",
      "description": "champion"
    },
    "skill": {
      "value": "Q",
      "description": "skill"
    },
    "range": {
      "value": "",
      "description": "range (deprecated)"
    },
    "target range": {
      "value": "340",
      "description": "target range"
    },
    "attack range": {
      "value": "",
      "description": "attack range"
    },
    "travel distance": {
      "value": "",
      "description": "travel distance"
    },
    "collision radius": {
      "value": "",
      "description": "collision radius"
    },
    "effect radius": {
      "value": "Kindred's <img src=\"https://vignette.wikia.nocookie.net/leagueoflegends/images/1/13/Range_icon.png/revision/latest/scale-to-width-down/15?cb=20170715002053\" \t alt=\"Range icon\"  \tclass=\"\" \t \tdata-image-key=\"Range_icon.png\" \tdata-image-name=\"Range icon.png\" \t \t width=\"15\"  \t height=\"15\"  \t \t \t \t> attack range",
      "description": "effect radius"
    },
    "width": {
      "value": "",
      "description": "width"
    },
    "angle": {
      "value": "",
      "description": "angle"
    },
    "inner radius": {
      "value": "",
      "description": "inner radius"
    },
    "tether radius": {
      "value": "",
      "description": "tether radius"
    },
    "speed": {
      "value": "500",
      "description": "speed"
    },
    "cast time": {
      "value": "none",
      "description": "cast time"
    },
    "cost": {
      "value": "35",
      "description": "cost"
    },
    "costtype": {
      "value": "Mana",
      "description": "costtype"
    },
    "static": {
      "value": "",
      "description": "static"
    },
    "cooldown": {
      "value": "9",
      "description": "cooldown"
    },
    "ontargetcd": {
      "value": "",
      "description": "ontargetcd"
    },
    "ontargetcdstatic": {
      "value": "",
      "description": "ontargetcdstatic"
    },
    "recharge": {
      "value": "",
      "description": "recharge"
    },
    "rechargestatic": {
      "value": "",
      "description": "rechargestatic"
    },
    "customlabel": {
      "value": "",
      "description": "customlabel"
    },
    "custominfo": {
      "value": "",
      "description": "custominfo"
    },
    "icon": {
      "value": "Dance of Arrows.png",
      "description": "icon"
    },
    "blurb": {
      "value": "Kindred tumbles and shoots up to three arrows at nearby targets.",
      "description": "blurb"
    },
    "blurb2": {
      "value": "",
      "description": "blurb2"
    },
    "description": {
      "value": "Active: Lamb <img src=\"https://vignette.wikia.nocookie.net/leagueoflegends/images/5/55/Dash.png/revision/latest/scale-to-width-down/20?cb=20180514002826\" \t alt=\"Dash\"  \tclass=\"\" \t \tdata-image-key=\"Dash.png\" \tdata-image-name=\"Dash.png\" \t \t width=\"20\"  \t height=\"20\"  \t \t \t \t> dashes in the target direction, gaining <img src=\"https://vignette.wikia.nocookie.net/leagueoflegends/images/9/91/Attack_speed_icon.png/revision/latest/scale-to-width-down/15?cb=20170515203443\" \t alt=\"Attack speed icon\"  \tclass=\"\" \t \tdata-image-key=\"Attack_speed_icon.png\" \tdata-image-name=\"Attack speed icon.png\" \t \t width=\"15\"  \t height=\"15\"  \t \t \t \t> 25% (+ 5% per <img src=\"https://vignette.wikia.nocookie.net/leagueoflegends/images/f/f5/Mark_of_the_Kindred.png/revision/latest/scale-to-width-down/20?cb=20170818190657\" \t alt=\"Mark of the Kindred\"  \tclass=\"thumbborder \" \t \tdata-image-key=\"Mark_of_the_Kindred.png\" \tdata-image-name=\"Mark of the Kindred.png\" \t \t width=\"20\"  \t height=\"20\"  \t \t \t \t> Mark) bonus attack speed for 4 seconds and firing up to three arrows to nearby <img src=\"https://vignette.wikia.nocookie.net/leagueoflegends/images/0/0e/Sight_icon.png/revision/latest/scale-to-width-down/20?cb=20130928145820\" \t alt=\"Sight icon\"  \tclass=\"\" \t \tdata-image-key=\"Sight_icon.png\" \tdata-image-name=\"Sight icon.png\" \t \t width=\"20\"  \t height=\"20\"  \t \t \t \t> visible targets after dashing, each one dealing physical damage. Lamb's current attack target at any proximity will be prioritized by one of the arrows.",
      "description": "description"
    },
    "leveling": {
      "value": "Physical Damage:60 / 80 / 100 / 120 / 140 (+ 65% bonus AD)",
      "description": "leveling"
    },
    "icon2": {
      "value": "",
      "description": "icon2"
    },
    "description2": {
      "value": "Casting <img src=\"https://vignette.wikia.nocookie.net/leagueoflegends/images/0/08/Wolf%27s_Frenzy.png/revision/latest/scale-to-width-down/20?cb=20170818190726\" \t alt=\"Wolf&amp;#039;s Frenzy\"  \tclass=\"thumbborder \" \t \tdata-image-key=\"Wolf%27s_Frenzy.png\" \tdata-image-name=\"Wolf&#39;s Frenzy.png\" \t \t width=\"20\"  \t height=\"20\"  \t \t \t \t> Wolf's Frenzy or using Dance of Arrows while inside its area will reduce this ability's <img src=\"https://vignette.wikia.nocookie.net/leagueoflegends/images/9/95/Cooldown_reduction_icon.png/revision/latest/scale-to-width-down/15?cb=20170515203444\" \t alt=\"Cooldown reduction icon\"  \tclass=\"\" \t \tdata-image-key=\"Cooldown_reduction_icon.png\" \tdata-image-name=\"Cooldown reduction icon.png\" \t \t width=\"15\"  \t height=\"15\"  \t \t \t \t> cooldown to an amount.",
      "description": "description2"
    },
    "leveling2": {
      "value": "Static Cooldown:4 / 3.5 / 3 / 2.5 / 2",
      "description": "leveling2"
    },
    "icon3": {
      "value": "",
      "description": "icon3"
    },
    "description3": {
      "value": "Lamb can cast any of her abilities during Dance of Arrows'  dash.",
      "description": "description3"
    },
    "leveling3": {
      "value": "",
      "description": "leveling3"
    },
    "icon4": {
      "value": "",
      "description": "icon4"
    },
    "description4": {
      "value": "Dance of Arrows <img src=\"https://vignette.wikia.nocookie.net/leagueoflegends/images/0/05/Bladework.png/revision/latest/scale-to-width-down/20?cb=20150721193304\" \t alt=\"Bladework\"  \tclass=\"\" \t \tdata-image-key=\"Bladework.png\" \tdata-image-name=\"Bladework.png\" \t \t width=\"20\"  \t height=\"20\"  \t \t \t \t> resets Lamb's basic attack timer.",
      "description": "description4"
    },
    "leveling4": {
      "value": "",
      "description": "leveling4"
    },
    "icon5": {
      "value": "",
      "description": "icon5"
    },
    "description5": {
      "value": "",
      "description": "description5"
    },
    "leveling5": {
      "value": "",
      "description": "leveling5"
    },
    "targeting": {
      "value": "Direction",
      "description": "Permafrost is a single target ability."
    },
    "affects": {
      "value": "Enemies",
      "description": "Permafrost affects enemy champions and large monsters"
    },
    "damagetype": {
      "value": "Physical",
      "description": "Permafrost deals magic damage."
    },
    "spelleffects": {
      "value": "Area of effect",
      "description": "spelleffects"
    },
    "onhiteffects": {
      "value": "",
      "description": "onhiteffects can be set to 'true', for abilities that apply on-hit effects (from items or other abilities)"
    },
    "occurrence": {
      "value": "",
      "description": "occurrence can either be set to 'hit' or 'attack', and refers to on-hit effects"
    },
    "spellshield": {
      "value": "True",
      "description": "spellshield can either be set to true, or written with a custom description."
    },
    "projectile": {
      "value": "True",
      "description": "true"
    },
    "callforhelp": {
      "value": "",
      "description": "callforhelp determines whether minion aggro will transfer to the caster"
    },
    "additional": {
      "value": "",
      "description": "Displays additional information in a smaller window below the template."
    },
    "notes": {
      "value": "* The dash does not have a fixed range, it can be directed by up to 340 units.\n The dash distance can be extended to up to 400 units when dashing across terrain.\n The cooldown will not be modified if it cannot be reduced (the current cooldown would have to be less than the reduction amount in this case).",
      "description": "Displays additional information with effect table to the right."
    },
    "flavorsound": {
      "value": "",
      "description": "flavor sound"
    },
    "video": {
      "value": "",
      "description": "video"
    },
    "video2": {
      "value": "",
      "description": "video 2"
    },
    "yvideo": {
      "value": "",
      "description": "YouTube video"
    },
    "yvideo2": {
      "value": "",
      "description": "YouTube video 2"
    }
  },
  {
    "1": {
      "value": "Wolf's Frenzy",
      "description": "Necessary: Used for identification."
    },
    "disp_name": {
      "value": "",
      "description": "Name of the ability\nOnly necessary if the value differs from Wolf's Frenzy."
    },
    "champion": {
      "value": "Kindred",
      "description": "champion"
    },
    "skill": {
      "value": "W",
      "description": "skill"
    },
    "range": {
      "value": "",
      "description": "range (deprecated)"
    },
    "target range": {
      "value": "500",
      "description": "target range"
    },
    "attack range": {
      "value": "",
      "description": "attack range"
    },
    "travel distance": {
      "value": "",
      "description": "travel distance"
    },
    "collision radius": {
      "value": "",
      "description": "collision radius"
    },
    "effect radius": {
      "value": "800",
      "description": "effect radius"
    },
    "width": {
      "value": "",
      "description": "width"
    },
    "angle": {
      "value": "",
      "description": "angle"
    },
    "inner radius": {
      "value": "",
      "description": "inner radius"
    },
    "tether radius": {
      "value": "",
      "description": "tether radius"
    },
    "speed": {
      "value": "1400",
      "description": "speed"
    },
    "cast time": {
      "value": "none",
      "description": "cast time"
    },
    "cost": {
      "value": "40",
      "description": "cost"
    },
    "costtype": {
      "value": "Mana",
      "description": "costtype"
    },
    "static": {
      "value": "",
      "description": "static"
    },
    "cooldown": {
      "value": "18 / 17 / 16 / 15 / 14",
      "description": "cooldown"
    },
    "ontargetcd": {
      "value": "",
      "description": "ontargetcd"
    },
    "ontargetcdstatic": {
      "value": "",
      "description": "ontargetcdstatic"
    },
    "recharge": {
      "value": "",
      "description": "recharge"
    },
    "rechargestatic": {
      "value": "",
      "description": "rechargestatic"
    },
    "customlabel": {
      "value": "",
      "description": "customlabel"
    },
    "custominfo": {
      "value": "",
      "description": "custominfo"
    },
    "icon": {
      "value": "Wolf's Frenzy.png",
      "description": "icon"
    },
    "blurb": {
      "value": "Wolf enrages and attacks enemies around him.",
      "description": "blurb"
    },
    "blurb2": {
      "value": "",
      "description": "blurb2"
    },
    "description": {
      "value": "Passive: As Kindred move and attack, they build up to 100 stacks of Hunter's Vigor. At full stacks, Lamb's next basic attack <img src=\"https://vignette.wikia.nocookie.net/leagueoflegends/images/7/76/Heal_power.png/revision/latest/scale-to-width-down/20?cb=20170909150244\" \t alt=\"Heal power\"  \tclass=\"\" \t \tdata-image-key=\"Heal_power.png\" \tdata-image-name=\"Heal power.png\" \t \t width=\"20\"  \t height=\"20\"  \t \t \t \t> heals her for up to 49 − 100 (based on level), based on Kindred's missing health.",
      "description": "description"
    },
    "leveling": {
      "value": "",
      "description": "leveling"
    },
    "icon2": {
      "value": "",
      "description": "icon2"
    },
    "description2": {
      "value": "Active: Wolf <img src=\"https://vignette.wikia.nocookie.net/leagueoflegends/images/5/55/Dash.png/revision/latest/scale-to-width-down/20?cb=20180514002826\" \t alt=\"Dash\"  \tclass=\"\" \t \tdata-image-key=\"Dash.png\" \tdata-image-name=\"Dash.png\" \t \t width=\"20\"  \t height=\"20\"  \t \t \t \t> dashes to the target location and claims the surrounding area as his territory for the next 8.5 seconds, separating from Lamb. Wolf autonomously attacks enemies within the area, prioritizing Lamb's attack target.",
      "description": "description2"
    },
    "leveling2": {
      "value": "",
      "description": "leveling2"
    },
    "icon3": {
      "value": "",
      "description": "icon3"
    },
    "description3": {
      "value": "Wolf's basic attacks deal magic damage and scale with 25% of Kindred's bonus attack speed. Against monsters, Wolf deals 50% increased damage and his attacks <img src=\"https://vignette.wikia.nocookie.net/leagueoflegends/images/7/78/Slow_icon.png/revision/latest/scale-to-width-down/20?cb=20171201224744\" \t alt=\"Slow icon\"  \tclass=\"\" \t \tdata-image-key=\"Slow_icon.png\" \tdata-image-name=\"Slow icon.png\" \t \t width=\"20\"  \t height=\"20\"  \t \t \t \t> slow the target by 50% for 2 seconds.",
      "description": "description3"
    },
    "leveling3": {
      "value": "Magic Damage:25 / 30 / 35 / 40 / 45 (+ 20% bonus AD) (+ 1.5% (+ 1% per <img src=\"https://vignette.wikia.nocookie.net/leagueoflegends/images/f/f5/Mark_of_the_Kindred.png/revision/latest/scale-to-width-down/20?cb=20170818190657\" \t alt=\"Mark of the Kindred\"  \tclass=\"thumbborder \" \t \tdata-image-key=\"Mark_of_the_Kindred.png\" \tdata-image-name=\"Mark of the Kindred.png\" \t \t width=\"20\"  \t height=\"20\"  \t \t \t \t> Mark) of target's current health)",
      "description": "leveling3"
    },
    "icon4": {
      "value": "",
      "description": "icon4"
    },
    "description4": {
      "value": "Wolf's Frenzy ends immediately if Lamb leaves the area or dies.",
      "description": "description4"
    },
    "leveling4": {
      "value": "",
      "description": "leveling4"
    },
    "icon5": {
      "value": "",
      "description": "icon5"
    },
    "description5": {
      "value": "",
      "description": "description5"
    },
    "leveling5": {
      "value": "",
      "description": "leveling5"
    },
    "targeting": {
      "value": "Ground",
      "description": "Permafrost is a single target ability."
    },
    "affects": {
      "value": "Enemies",
      "description": "Permafrost affects enemy champions and large monsters"
    },
    "damagetype": {
      "value": "Magic",
      "description": "Permafrost deals magic damage."
    },
    "spelleffects": {
      "value": "Area of effect",
      "description": "spelleffects"
    },
    "onhiteffects": {
      "value": "",
      "description": "onhiteffects can be set to 'true', for abilities that apply on-hit effects (from items or other abilities)"
    },
    "occurrence": {
      "value": "",
      "description": "occurrence can either be set to 'hit' or 'attack', and refers to on-hit effects"
    },
    "spellshield": {
      "value": "True",
      "description": "spellshield can either be set to true, or written with a custom description."
    },
    "projectile": {
      "value": "False",
      "description": "true"
    },
    "callforhelp": {
      "value": "",
      "description": "callforhelp determines whether minion aggro will transfer to the caster"
    },
    "additional": {
      "value": "",
      "description": "Displays additional information in a smaller window below the template."
    },
    "notes": {
      "value": "* Wolf is <img src=\"https://vignette.wikia.nocookie.net/leagueoflegends/images/9/9c/Playful.png/revision/latest/scale-to-width-down/20?cb=20161018215400\" \t alt=\"Playful\"  \tclass=\"\" \t \tdata-image-key=\"Playful.png\" \tdata-image-name=\"Playful.png\" \t \t width=\"20\"  \t height=\"20\"  \t \t \t \t> untargetable and <img src=\"https://vignette.wikia.nocookie.net/leagueoflegends/images/a/ab/Ghost.png/revision/latest/scale-to-width-down/20?cb=20180514003209\" \t alt=\"Ghost\"  \tclass=\"\" \t \tdata-image-key=\"Ghost.png\" \tdata-image-name=\"Ghost.png\" \t \t width=\"20\"  \t height=\"20\"  \t \t \t \t> ghosted but he cannot move through terrain other than the initial dash on activation.\n Wolf is not able to re-target <img src=\"https://vignette.wikia.nocookie.net/leagueoflegends/images/a/a2/Rift_ScuttlerSquare.png/revision/latest/scale-to-width-down/20?cb=20141111231735\" \t alt=\"Rift ScuttlerSquare\"  \tclass=\"thumbborder \" \t \tdata-image-key=\"Rift_ScuttlerSquare.png\" \tdata-image-name=\"Rift ScuttlerSquare.png\" \t \t width=\"20\"  \t height=\"20\"  \t \t \t \t> Rift Scuttler if he loses <img src=\"https://vignette.wikia.nocookie.net/leagueoflegends/images/0/0e/Sight_icon.png/revision/latest/scale-to-width-down/20?cb=20130928145820\" \t alt=\"Sight icon\"  \tclass=\"\" \t \tdata-image-key=\"Sight_icon.png\" \tdata-image-name=\"Sight icon.png\" \t \t width=\"20\"  \t height=\"20\"  \t \t \t \t> sight of her while he's attacking it.\n Wolf's Frenzy does not end if Lamb enters <img src=\"https://vignette.wikia.nocookie.net/leagueoflegends/images/7/7c/Revival_icon.png/revision/latest/scale-to-width-down/20?cb=20170714051127\" \t alt=\"Revival icon\"  \tclass=\"\" \t \tdata-image-key=\"Revival_icon.png\" \tdata-image-name=\"Revival icon.png\" \t \t width=\"20\"  \t height=\"20\"  \t \t \t \t> resurrection.",
      "description": "Displays additional information with effect table to the right."
    },
    "flavorsound": {
      "value": "",
      "description": "flavor sound"
    },
    "video": {
      "value": "",
      "description": "video"
    },
    "video2": {
      "value": "",
      "description": "video 2"
    },
    "yvideo": {
      "value": "",
      "description": "YouTube video"
    },
    "yvideo2": {
      "value": "",
      "description": "YouTube video 2"
    }
  },
  {
    "1": {
      "value": "Mounting Dread",
      "description": "Necessary: Used for identification."
    },
    "disp_name": {
      "value": "",
      "description": "Name of the ability\nOnly necessary if the value differs from Mounting Dread."
    },
    "champion": {
      "value": "Kindred",
      "description": "champion"
    },
    "skill": {
      "value": "E",
      "description": "skill"
    },
    "range": {
      "value": "",
      "description": "range (deprecated)"
    },
    "target range": {
      "value": "<img src=\"https://vignette.wikia.nocookie.net/leagueoflegends/images/7/71/Range_model.png/revision/latest/scale-to-width-down/20?cb=20150616134216\" \t alt=\"Range model\"  \tclass=\"\" \t \tdata-image-key=\"Range_model.png\" \tdata-image-name=\"Range model.png\" \t \t width=\"20\"  \t height=\"20\"  \t \t \t \t> 500 − 750 (based on Marks)",
      "description": "target range"
    },
    "attack range": {
      "value": "",
      "description": "attack range"
    },
    "travel distance": {
      "value": "",
      "description": "travel distance"
    },
    "collision radius": {
      "value": "",
      "description": "collision radius"
    },
    "effect radius": {
      "value": "",
      "description": "effect radius"
    },
    "width": {
      "value": "",
      "description": "width"
    },
    "angle": {
      "value": "",
      "description": "angle"
    },
    "inner radius": {
      "value": "",
      "description": "inner radius"
    },
    "tether radius": {
      "value": "",
      "description": "tether radius"
    },
    "speed": {
      "value": "",
      "description": "speed"
    },
    "cast time": {
      "value": "0.25",
      "description": "cast time"
    },
    "cost": {
      "value": "50",
      "description": "cost"
    },
    "costtype": {
      "value": "Mana",
      "description": "costtype"
    },
    "static": {
      "value": "",
      "description": "static"
    },
    "cooldown": {
      "value": "16 / 15 / 14 / 13 / 12",
      "description": "cooldown"
    },
    "ontargetcd": {
      "value": "",
      "description": "ontargetcd"
    },
    "ontargetcdstatic": {
      "value": "",
      "description": "ontargetcdstatic"
    },
    "recharge": {
      "value": "",
      "description": "recharge"
    },
    "rechargestatic": {
      "value": "",
      "description": "rechargestatic"
    },
    "customlabel": {
      "value": "",
      "description": "customlabel"
    },
    "custominfo": {
      "value": "",
      "description": "custominfo"
    },
    "icon": {
      "value": "Mounting Dread.png",
      "description": "icon"
    },
    "blurb": {
      "value": "Lamb fires a carefully placed shot, slowing the target. If Lamb attacks the target two more times, her third attack instead directs Wolf to pounce on the enemy, savaging them for massive damage.",
      "description": "blurb"
    },
    "blurb2": {
      "value": "",
      "description": "blurb2"
    },
    "description": {
      "value": "Active: Lamb applies a mark to the target enemy for 4 seconds and cripples them, <img src=\"https://vignette.wikia.nocookie.net/leagueoflegends/images/7/78/Slow_icon.png/revision/latest/scale-to-width-down/20?cb=20171201224744\" \t alt=\"Slow icon\"  \tclass=\"\" \t \tdata-image-key=\"Slow_icon.png\" \tdata-image-name=\"Slow icon.png\" \t \t width=\"20\"  \t height=\"20\"  \t \t \t \t> slowing them by 50% for 1 second.",
      "description": "description"
    },
    "leveling": {
      "value": "",
      "description": "leveling"
    },
    "icon2": {
      "value": "",
      "description": "icon2"
    },
    "description2": {
      "value": "Lamb's attacks against the target refreshes the mark's duration. If she manages to basic attack the marked target twice, her third attack directs Wolf to pounce them, consuming the mark to deal bonus physical damage, capped at 300 against <img src=\"https://vignette.wikia.nocookie.net/leagueoflegends/images/d/d1/Monster_icon.png/revision/latest?cb=20181123222641\" \t alt=\"Monster icon\"  \tclass=\"\" \t \tdata-image-key=\"Monster_icon.png\" \tdata-image-name=\"Monster icon.png\" \t \t width=\"20\"  \t height=\"20\"  \t \t \t \t> monsters.",
      "description": "description2"
    },
    "leveling2": {
      "value": "Bonus Physical Damage:80 / 100 / 120 / 140 / 160 (+ 80% bonus AD) (+ 8% (+ 0.5% per <img src=\"https://vignette.wikia.nocookie.net/leagueoflegends/images/f/f5/Mark_of_the_Kindred.png/revision/latest/scale-to-width-down/20?cb=20170818190657\" \t alt=\"Mark of the Kindred\"  \tclass=\"thumbborder \" \t \tdata-image-key=\"Mark_of_the_Kindred.png\" \tdata-image-name=\"Mark of the Kindred.png\" \t \t width=\"20\"  \t height=\"20\"  \t \t \t \t> Mark) of target's missing health)",
      "description": "leveling2"
    },
    "icon3": {
      "value": "",
      "description": "icon3"
    },
    "description3": {
      "value": "Wolf's pounce will <img src=\"https://vignette.wikia.nocookie.net/leagueoflegends/images/4/41/Critical_strike_icon.png/revision/latest/scale-to-width-down/20?cb=20191126102550\" \t alt=\"Critical strike icon\"  \tclass=\"\" \t \tdata-image-key=\"Critical_strike_icon.png\" \tdata-image-name=\"Critical strike icon.png\" \t \t width=\"20\"  \t height=\"20\"  \t \t \t \t> critically strike for (50% + <img src=\"https://vignette.wikia.nocookie.net/leagueoflegends/images/1/15/Infinity_Edge_item.png/revision/latest/scale-to-width-down/20?cb=20180531105945\" \t alt=\"Infinity Edge item\"  \tclass=\"thumbborder \" \t \tdata-image-key=\"Infinity_Edge_item.png\" \tdata-image-name=\"Infinity Edge item.png\" \t \t width=\"20\"  \t height=\"20\"  \t \t \t \t> 37.5%) bonus physical damage against targets below 15% − 65% (based on critical strike chance) of their <img src=\"https://vignette.wikia.nocookie.net/leagueoflegends/images/1/17/Health_icon.png/revision/latest/scale-to-width-down/15?cb=20170515203537\" \t alt=\"Health icon\"  \tclass=\"\" \t \tdata-image-key=\"Health_icon.png\" \tdata-image-name=\"Health icon.png\" \t \t width=\"15\"  \t height=\"15\"  \t \t \t \t> maximum health.",
      "description": "description3"
    },
    "leveling3": {
      "value": "",
      "description": "leveling3"
    },
    "icon4": {
      "value": "",
      "description": "icon4"
    },
    "description4": {
      "value": "",
      "description": "description4"
    },
    "leveling4": {
      "value": "",
      "description": "leveling4"
    },
    "icon5": {
      "value": "",
      "description": "icon5"
    },
    "description5": {
      "value": "",
      "description": "description5"
    },
    "leveling5": {
      "value": "",
      "description": "leveling5"
    },
    "targeting": {
      "value": "Unit",
      "description": "Permafrost is a single target ability."
    },
    "affects": {
      "value": "Enemies",
      "description": "Permafrost affects enemy champions and large monsters"
    },
    "damagetype": {
      "value": "Physical",
      "description": "Permafrost deals magic damage."
    },
    "spelleffects": {
      "value": "spell",
      "description": "spelleffects"
    },
    "onhiteffects": {
      "value": "",
      "description": "onhiteffects can be set to 'true', for abilities that apply on-hit effects (from items or other abilities)"
    },
    "occurrence": {
      "value": "",
      "description": "occurrence can either be set to 'hit' or 'attack', and refers to on-hit effects"
    },
    "spellshield": {
      "value": "True",
      "description": "spellshield can either be set to true, or written with a custom description."
    },
    "projectile": {
      "value": "True",
      "description": "true"
    },
    "callforhelp": {
      "value": "",
      "description": "callforhelp determines whether minion aggro will transfer to the caster"
    },
    "additional": {
      "value": "",
      "description": "Displays additional information in a smaller window below the template."
    },
    "notes": {
      "value": "* The bonus damage will not benefit from <img src=\"https://vignette.wikia.nocookie.net/leagueoflegends/images/4/41/Critical_strike_icon.png/revision/latest/scale-to-width-down/20?cb=20191126102550\" \t alt=\"Critical strike icon\"  \tclass=\"\" \t \tdata-image-key=\"Critical_strike_icon.png\" \tdata-image-name=\"Critical strike icon.png\" \t \t width=\"20\"  \t height=\"20\"  \t \t \t \t> critical strikes unless the target is below the maximum health condition.",
      "description": "Displays additional information with effect table to the right."
    },
    "flavorsound": {
      "value": "",
      "description": "flavor sound"
    },
    "video": {
      "value": "",
      "description": "video"
    },
    "video2": {
      "value": "",
      "description": "video 2"
    },
    "yvideo": {
      "value": "",
      "description": "YouTube video"
    },
    "yvideo2": {
      "value": "",
      "description": "YouTube video 2"
    }
  },
  {
    "1": {
      "value": "Lamb's Respite",
      "description": "Necessary: Used for identification."
    },
    "disp_name": {
      "value": "",
      "description": "Name of the ability\nOnly necessary if the value differs from Lamb's Respite."
    },
    "champion": {
      "value": "Kindred",
      "description": "champion"
    },
    "skill": {
      "value": "R",
      "description": "skill"
    },
    "range": {
      "value": "",
      "description": "range (deprecated)"
    },
    "target range": {
      "value": "",
      "description": "target range"
    },
    "attack range": {
      "value": "",
      "description": "attack range"
    },
    "travel distance": {
      "value": "",
      "description": "travel distance"
    },
    "collision radius": {
      "value": "",
      "description": "collision radius"
    },
    "effect radius": {
      "value": "500",
      "description": "effect radius"
    },
    "width": {
      "value": "",
      "description": "width"
    },
    "angle": {
      "value": "",
      "description": "angle"
    },
    "inner radius": {
      "value": "",
      "description": "inner radius"
    },
    "tether radius": {
      "value": "",
      "description": "tether radius"
    },
    "speed": {
      "value": "",
      "description": "speed"
    },
    "cast time": {
      "value": "None",
      "description": "cast time"
    },
    "cost": {
      "value": "100",
      "description": "cost"
    },
    "costtype": {
      "value": "Mana",
      "description": "costtype"
    },
    "static": {
      "value": "",
      "description": "static"
    },
    "cooldown": {
      "value": "180 / 165 / 150 / 135 / 120",
      "description": "cooldown"
    },
    "ontargetcd": {
      "value": "",
      "description": "ontargetcd"
    },
    "ontargetcdstatic": {
      "value": "",
      "description": "ontargetcdstatic"
    },
    "recharge": {
      "value": "",
      "description": "recharge"
    },
    "rechargestatic": {
      "value": "",
      "description": "rechargestatic"
    },
    "customlabel": {
      "value": "",
      "description": "customlabel"
    },
    "custominfo": {
      "value": "",
      "description": "custominfo"
    },
    "icon": {
      "value": "Lamb's Respite.png",
      "description": "icon"
    },
    "blurb": {
      "value": "Lamb grants all living things inside a zone a respite from death. Until the effect ends, nothing can die. At the end, units are healed.",
      "description": "blurb"
    },
    "blurb2": {
      "value": "",
      "description": "blurb2"
    },
    "description": {
      "value": "Active: Lamb blesses the ground under herself for 4 seconds and enters a 0.264 seconds cast time. All units inside the zone cannot be reduced below <img src=\"https://vignette.wikia.nocookie.net/leagueoflegends/images/1/17/Health_icon.png/revision/latest/scale-to-width-down/15?cb=20170515203537\" \t alt=\"Health icon\"  \tclass=\"\" \t \tdata-image-key=\"Health_icon.png\" \tdata-image-name=\"Health icon.png\" \t \t width=\"15\"  \t height=\"15\"  \t \t \t \t> 10% of their maximum health, and will become <img src=\"https://vignette.wikia.nocookie.net/leagueoflegends/images/c/c1/Cosmic_Radiance.png/revision/latest/scale-to-width-down/20?cb=20160608034537\" \t alt=\"Cosmic Radiance\"  \tclass=\"\" \t \tdata-image-key=\"Cosmic_Radiance.png\" \tdata-image-name=\"Cosmic Radiance.png\" \t \t width=\"20\"  \t height=\"20\"  \t \t \t \t> invulnerable for the remaining duration when they reach or are at the threshold, during which they also cannot be <img src=\"https://vignette.wikia.nocookie.net/leagueoflegends/images/7/76/Heal_power.png/revision/latest/scale-to-width-down/20?cb=20170909150244\" \t alt=\"Heal power\"  \tclass=\"\" \t \tdata-image-key=\"Heal_power.png\" \tdata-image-name=\"Heal power.png\" \t \t width=\"20\"  \t height=\"20\"  \t \t \t \t> healed, but can still <img src=\"https://vignette.wikia.nocookie.net/leagueoflegends/images/3/31/Health_regeneration_icon.png/revision/latest/scale-to-width-down/15?cb=20170515203536\" \t alt=\"Health regeneration icon\"  \tclass=\"\" \t \tdata-image-key=\"Health_regeneration_icon.png\" \tdata-image-name=\"Health regeneration icon.png\" \t \t width=\"15\"  \t height=\"15\"  \t \t \t \t> regenerate health.",
      "description": "description"
    },
    "leveling": {
      "value": "",
      "description": "leveling"
    },
    "icon2": {
      "value": "",
      "description": "icon2"
    },
    "description2": {
      "value": "",
      "description": "description2"
    },
    "leveling2": {
      "value": "",
      "description": "leveling2"
    },
    "icon3": {
      "value": "",
      "description": "icon3"
    },
    "description3": {
      "value": "All targetable units within the zone are <img src=\"https://vignette.wikia.nocookie.net/leagueoflegends/images/7/76/Heal_power.png/revision/latest/scale-to-width-down/20?cb=20170909150244\" \t alt=\"Heal power\"  \tclass=\"\" \t \tdata-image-key=\"Heal_power.png\" \tdata-image-name=\"Heal power.png\" \t \t width=\"20\"  \t height=\"20\"  \t \t \t \t> healed immediately when the blessing ends.",
      "description": "description3"
    },
    "leveling3": {
      "value": "Heal:250 / 287.5 / 325 / 362.5 / 400",
      "description": "leveling3"
    },
    "icon4": {
      "value": "",
      "description": "icon4"
    },
    "description4": {
      "value": "",
      "description": "description4"
    },
    "leveling4": {
      "value": "",
      "description": "leveling4"
    },
    "icon5": {
      "value": "",
      "description": "icon5"
    },
    "description5": {
      "value": "",
      "description": "description5"
    },
    "leveling5": {
      "value": "",
      "description": "leveling5"
    },
    "targeting": {
      "value": "None",
      "description": "Permafrost is a single target ability."
    },
    "affects": {
      "value": "Self, Allies, Enemies",
      "description": "Permafrost affects enemy champions and large monsters"
    },
    "damagetype": {
      "value": "",
      "description": "Permafrost deals magic damage."
    },
    "spelleffects": {
      "value": "Heal",
      "description": "spelleffects"
    },
    "onhiteffects": {
      "value": "",
      "description": "onhiteffects can be set to 'true', for abilities that apply on-hit effects (from items or other abilities)"
    },
    "occurrence": {
      "value": "",
      "description": "occurrence can either be set to 'hit' or 'attack', and refers to on-hit effects"
    },
    "spellshield": {
      "value": "",
      "description": "spellshield can either be set to true, or written with a custom description."
    },
    "projectile": {
      "value": "",
      "description": "true"
    },
    "callforhelp": {
      "value": "",
      "description": "callforhelp determines whether minion aggro will transfer to the caster"
    },
    "additional": {
      "value": "",
      "description": "Displays additional information in a smaller window below the template."
    },
    "notes": {
      "value": "* Lamb's Respite will affect all <img src=\"https://vignette.wikia.nocookie.net/leagueoflegends/images/2/25/Champion_icon.png/revision/latest/scale-to-width-down/20?cb=20181122022630\" \t alt=\"Champion icon\"  \tclass=\"\" \t \tdata-image-key=\"Champion_icon.png\" \tdata-image-name=\"Champion icon.png\" \t \t width=\"20\"  \t height=\"20\"  \t \t \t \t> champions, <img src=\"https://vignette.wikia.nocookie.net/leagueoflegends/images/3/30/Minion_icon.png/revision/latest/scale-to-width-down/20?cb=20180701050249\" \t alt=\"Minion icon\"  \tclass=\"\" \t \tdata-image-key=\"Minion_icon.png\" \tdata-image-name=\"Minion icon.png\" \t \t width=\"20\"  \t height=\"20\"  \t \t \t \t> minions, and <img src=\"https://vignette.wikia.nocookie.net/leagueoflegends/images/d/d1/Monster_icon.png/revision/latest?cb=20181123222641\" \t alt=\"Monster icon\"  \tclass=\"\" \t \tdata-image-key=\"Monster_icon.png\" \tdata-image-name=\"Monster icon.png\" \t \t width=\"20\"  \t height=\"20\"  \t \t \t \t> monsters, but not <img src=\"https://vignette.wikia.nocookie.net/leagueoflegends/images/f/f1/Ward_icon.png/revision/latest/scale-to-width-down/20?cb=20180828001331\" \t alt=\"Ward icon\"  \tclass=\"\" \t \tdata-image-key=\"Ward_icon.png\" \tdata-image-name=\"Ward icon.png\" \t \t width=\"20\"  \t height=\"20\"  \t \t \t \t> wards, <img src=\"https://vignette.wikia.nocookie.net/leagueoflegends/images/8/82/Turret_icon.png/revision/latest/scale-to-width-down/20?cb=20180701054101\" \t alt=\"Turret icon\"  \tclass=\"\" \t \tdata-image-key=\"Turret_icon.png\" \tdata-image-name=\"Turret icon.png\" \t \t width=\"20\"  \t height=\"20\"  \t \t \t \t> turrets, or jungle plants.\n Lamb's Respite will affect <img src=\"https://vignette.wikia.nocookie.net/leagueoflegends/images/9/9c/Playful.png/revision/latest/scale-to-width-down/20?cb=20161018215400\" \t alt=\"Playful\"  \tclass=\"\" \t \tdata-image-key=\"Playful.png\" \tdata-image-name=\"Playful.png\" \t \t width=\"20\"  \t height=\"20\"  \t \t \t \t> untargetable units but does not grant them the <img src=\"https://vignette.wikia.nocookie.net/leagueoflegends/images/7/76/Heal_power.png/revision/latest/scale-to-width-down/20?cb=20170909150244\" \t alt=\"Heal power\"  \tclass=\"\" \t \tdata-image-key=\"Heal_power.png\" \tdata-image-name=\"Heal power.png\" \t \t width=\"20\"  \t height=\"20\"  \t \t \t \t> heal at the end of the blessing.\n <img src=\"https://vignette.wikia.nocookie.net/leagueoflegends/images/8/85/Death_from_Below.png/revision/latest/scale-to-width-down/20?cb=20180516185259\" \t alt=\"Death from Below\"  \tclass=\"\" \t \tdata-image-key=\"Death_from_Below.png\" \tdata-image-name=\"Death from Below.png\" \t \t width=\"20\"  \t height=\"20\"  \t \t \t \t> Execution effects will bypass Lamb's Respite threshold and leave the unit at 1 health. This does not occur if the unit is at the threshold, as they are <img src=\"https://vignette.wikia.nocookie.net/leagueoflegends/images/c/c1/Cosmic_Radiance.png/revision/latest/scale-to-width-down/20?cb=20160608034537\" \t alt=\"Cosmic Radiance\"  \tclass=\"\" \t \tdata-image-key=\"Cosmic_Radiance.png\" \tdata-image-name=\"Cosmic Radiance.png\" \t \t width=\"20\"  \t height=\"20\"  \t \t \t \t> invulnerable.\n <img src=\"https://vignette.wikia.nocookie.net/leagueoflegends/images/1/15/Health_resource.png/revision/latest/scale-to-width-down/20?cb=20200102184938\" \t alt=\"Health resource\"  \tclass=\"\" \t \tdata-image-key=\"Health_resource.png\" \tdata-image-name=\"Health resource.png\" \t \t width=\"20\"  \t height=\"20\"  \t \t \t \t> Health costs will ignore Lamb's Respite's threshold.\n The cost will not be paid if the caster is below the threshold.\n\n Lamb's Respite has no effect on <img src=\"https://vignette.wikia.nocookie.net/leagueoflegends/images/c/c2/Omen_of_Death.png/revision/latest/scale-to-width-down/20?cb=20130929123503\" \t alt=\"Omen of Death\"  \tclass=\"\" \t \tdata-image-key=\"Omen_of_Death.png\" \tdata-image-name=\"Omen of Death.png\" \t \t width=\"20\"  \t height=\"20\"  \t \t \t \t> zombie state units.\n The effects are applied before the cast time.",
      "description": "Displays additional information with effect table to the right."
    },
    "flavorsound": {
      "value": "\"Shine once more, before the end.\"",
      "description": "flavor sound"
    },
    "video": {
      "value": "",
      "description": "video"
    },
    "video2": {
      "value": "",
      "description": "video 2"
    },
    "yvideo": {
      "value": "",
      "description": "YouTube video"
    },
    "yvideo2": {
      "value": "",
      "description": "YouTube video 2"
    }
  }
]